{"analysis":{"attitude":"Neutral","attitude_confidence":0.0,"subject":"Other","subject_confidence":0.0},"children":[{"analysis":{"attitude":"Neutral","attitude_confidence":0.7684450447559357,"subject":"Other","subject_confidence":0.702323853969574},"children":[{"analysis":{"attitude":"Neutral","attitude_confidence":0.7633965909481049,"subject":"Other","subject_confidence":0.7984126061201096},"children":[{"analysis":{"attitude":"Inquisitive","attitude_confidence":0.5733346343040466,"subject":"Discussion","subject_confidence":0.4751390218734741},"children":[{"analysis":{"attitude":"Neutral","attitude_confidence":0.7972142696380615,"subject":"Other","subject_confidence":0.8444765508174896},"children":[{"analysis":{"attitude":"Inquisitive","attitude_confidence":0.32655173540115356,"subject":"Other","subject_confidence":0.7732403874397278},"children":[]}]}]}]},{"analysis":{"attitude":"Inquisitive","attitude_confidence":0.47720402479171753,"subject":"Discussion","subject_confidence":0.33368462324142456},"children":[{"analysis":{"attitude":"Neutral","attitude_confidence":0.7539444714784622,"subject":"Other","subject_confidence":0.8353375941514969},"children":[{"analysis":{"attitude":"Neutral","attitude_confidence":0.781896561384201,"subject":"Other","subject_confidence":0.7850237935781479},"children":[]}]}]}]},{"analysis":{"attitude":"Praise","attitude_confidence":0.7477779984474182,"subject":"Other","subject_confidence":0.7206133604049683},"children":[]},{"analysis":{"attitude":"Neutral","attitude_confidence":0.6354374289512634,"subject":"Other","subject_confidence":0.7317295670509338},"children":[]}]}