{"analysis":{"attitude":"Inquisitive","attitude_confidence":0.32428357005119324,"subject":"Other","subject_confidence":0.78385029733181},"children":[{"analysis":{"attitude":"Disagreement","attitude_confidence":0.31692877411842346,"subject":"Other","subject_confidence":0.7591248005628586},"children":[{"analysis":{"attitude":"Inquisitive","attitude_confidence":0.43337583541870117,"subject":"Personal","subject_confidence":0.3154159486293793},"children":[{"analysis":{"attitude":"Neutral","attitude_confidence":0.7429824769496918,"subject":"Other","subject_confidence":0.7606275081634521},"children":[{"analysis":{"attitude":"Praise","attitude_confidence":0.7642089128494263,"subject":"Other","subject_confidence":0.7692174762487411},"children":[{"analysis":{"attitude":"Agreement","attitude_confidence":0.39582884311676025,"subject":"Discussion","subject_confidence":0.3426525890827179},"children":[]}]},{"analysis":{"attitude":"Inquisitive","attitude_confidence":0.3312991261482239,"subject":"Other","subject_confidence":0.809602752327919},"children":[{"analysis":{"attitude":"Neutral","attitude_confidence":0.7615123093128204,"subject":"Other","subject_confidence":0.7877815812826157},"children":[]}]}]}]}]},{"analysis":{"attitude":"Neutral","attitude_confidence":0.7955500930547714,"subject":"Other","subject_confidence":0.7673376947641373},"children":[{"analysis":{"attitude":"Praise","attitude_confidence":0.7802487015724182,"subject":"Other","subject_confidence":0.7152938842773438},"children":[]}]},{"analysis":{"attitude":"Neutral","attitude_confidence":0.7737147212028503,"subject":"Other","subject_confidence":0.7629368454217911},"children":[]}]}