{"analysis":{"attitude":"Neutral","attitude_confidence":0.0,"subject":"Other","subject_confidence":0.0},"children":[{"analysis":{"attitude":"Neutral","attitude_confidence":0.7581411004066467,"subject":"Other","subject_confidence":0.8189120590686798},"children":[]},{"analysis":{"attitude":"Neutral","attitude_confidence":0.7563255131244659,"subject":"Other","subject_confidence":0.8074020743370056},"children":[]},{"analysis":{"attitude":"Neutral","attitude_confidence":0.7807251363992691,"subject":"Animals","subject_confidence":0.5379527807235718},"children":[]},{"analysis":{"attitude":"Neutral","attitude_confidence":0.7792234271764755,"subject":"Other","subject_confidence":0.7171955704689026},"children":[]},{"analysis":{"attitude":"Neutral","attitude_confidence":0.7816559076309204,"subject":"Other","subject_confidence":0.8102039843797684},"children":[{"analysis":{"attitude":"Agreement","attitude_confidence":0.433881014585495,"subject":"Other","subject_confidence":0.7187024354934692},"children":[]}]},{"analysis":{"attitude":"Inquisitive","attitude_confidence":0.3294069170951843,"subject":"Other","subject_confidence":0.8305796831846237},"children":[]},{"analysis":{"attitude":"Neutral","attitude_confidence":0.7895908504724503,"subject":"Other","subject_confidence":0.8027817159891129},"children":[]},{"analysis":{"attitude":"Neutral","attitude_confidence":0.7468579709529877,"subject":"Other","subject_confidence":0.8084780126810074},"children":[]},{"analysis":{"attitude":"Praise","attitude_confidence":0.3846837282180786,"subject":"Other","subject_confidence":0.808631494641304},"children":[]}]}