{"analysis":{"attitude":"Neutral","attitude_confidence":0.7447415888309479,"subject":"Other","subject_confidence":0.7938306629657745},"children":[{"analysis":{"attitude":"Neutral","attitude_confidence":0.7828719913959503,"subject":"Other","subject_confidence":0.8293252289295197},"children":[]},{"analysis":{"attitude":"Agreement","attitude_confidence":0.6792187690734863,"subject":"Other","subject_confidence":0.7086678147315979},"children":[]},{"analysis":{"attitude":"Neutral","attitude_confidence":0.7311540842056274,"subject":"Other","subject_confidence":0.8322053402662277},"children":[]}]}