{"analysis":{"attitude":"Neutral","attitude_confidence":0.0,"subject":"Other","subject_confidence":0.0},"children":[{"analysis":{"attitude":"Neutral","attitude_confidence":0.7671946585178375,"subject":"Movies","subject_confidence":0.3056275248527527},"children":[{"analysis":{"attitude":"Neutral","attitude_confidence":0.7675377726554871,"subject":"Discussion","subject_confidence":0.47303080558776855},"children":[]}]},{"analysis":{"attitude":"Praise","attitude_confidence":0.43136218190193176,"subject":"Other","subject_confidence":0.792606309056282},"children":[]},{"analysis":{"attitude":"Praise","attitude_confidence":0.7341116666793823,"subject":"Other","subject_confidence":0.8160905539989471},"children":[]},{"analysis":{"attitude":"Inquisitive","attitude_confidence":0.4445461928844452,"subject":"Other","subject_confidence":0.8292055130004883},"children":[]},{"analysis":{"attitude":"Condemnation","attitude_confidence":0.30510973930358887,"subject":"Discussion","subject_confidence":0.32616785168647766},"children":[]},{"analysis":{"attitude":"Praise","attitude_confidence":0.43917417526245117,"subject":"Religion","subject_confidence":0.41318628191947937},"children":[]},{"analysis":{"attitude":"Praise","attitude_confidence":0.7911189794540405,"subject":"Other","subject_confidence":0.7815185189247131},"children":[]},{"analysis":{"attitude":"Praise","attitude_confidence":0.6238603591918945,"subject":"Other","subject_confidence":0.7536542117595673},"children":[]},{"analysis":{"attitude":"Neutral","attitude_confidence":0.7734890282154083,"subject":"Other","subject_confidence":0.7412861883640289},"children":[]}]}