{"analysis":{"attitude":"Neutral","attitude_confidence":0.0,"subject":"Other","subject_confidence":0.0},"children":[{"analysis":{"attitude":"Neutral","attitude_confidence":0.8145892918109894,"subject":"Joke","subject_confidence":0.5737170577049255},"children":[]},{"analysis":{"attitude":"Neutral","attitude_confidence":0.7220928370952606,"subject":"Joke","subject_confidence":0.30273711681365967},"children":[{"analysis":{"attitude":"Disagreement","attitude_confidence":0.33198896050453186,"subject":"Other","subject_confidence":0.7645968049764633},"children":[]}]},{"analysis":{"attitude":"Praise","attitude_confidence":0.487927109003067,"subject":"Other","subject_confidence":0.7417347133159637},"children":[]},{"analysis":{"attitude":"Disagreement","attitude_confidence":0.47899681329727173,"subject":"Other","subject_confidence":0.7979840934276581},"children":[]},{"analysis":{"attitude":"Neutral","attitude_confidence":0.7766183018684387,"subject":"Other","subject_confidence":0.7914929687976837},"children":[{"analysis":{"attitude":"Neutral","attitude_confidence":0.7885146737098694,"subject":"Other","subject_confidence":0.8049292862415314},"children":[{"analysis":{"attitude":"Inquisitive","attitude_confidence":0.5415453314781189,"subject":"Other","subject_confidence":0.8413017839193344},"children":[{"analysis":{"attitude":"Neutral","attitude_confidence":0.7975265681743622,"subject":"Other","subject_confidence":0.8545482158660889},"children":[]}]}]},{"analysis":{"attitude":"Praise","attitude_confidence":0.34803450107574463,"subject":"Other","subject_confidence":0.7998693734407425},"children":[]}]}]}