{"analysis":{"attitude":"Neutral","attitude_confidence":0.0,"subject":"Other","subject_confidence":0.0},"children":[{"analysis":{"attitude":"Neutral","attitude_confidence":0.7769669443368912,"subject":"Other","subject_confidence":0.7608491778373718},"children":[{"analysis":{"attitude":"Neutral","attitude_confidence":0.7951447814702988,"subject":"Other","subject_confidence":0.7734250575304031},"children":[]}]},{"analysis":{"attitude":"Inquisitive","attitude_confidence":0.7258614897727966,"subject":"Technology","subject_confidence":0.3144717812538147},"children":[]},{"analysis":{"attitude":"Neutral","attitude_confidence":0.8045604526996613,"subject":"Other","subject_confidence":0.8214630633592606},"children":[{"analysis":{"attitude":"Neutral","attitude_confidence":0.7666833698749542,"subject":"Other","subject_confidence":0.7426438629627228},"children":[]}]},{"analysis":{"attitude":"Praise","attitude_confidence":0.7117182612419128,"subject":"Other","subject_confidence":0.7491095960140228},"children":[{"analysis":{"attitude":"Condemnation","attitude_confidence":0.35350194573402405,"subject":"Discussion","subject_confidence":0.30787333846092224},"children":[]}]},{"analysis":{"attitude":"Neutral","attitude_confidence":0.7917290776968002,"subject":"Personal","subject_confidence":0.3131209909915924},"children":[]},{"analysis":{"attitude":"Neutral","attitude_confidence":0.8012444972991943,"subject":"Other","subject_confidence":0.7281841337680817},"children":[]},{"analysis":{"attitude":"Praise","attitude_confidence":0.5546866059303284,"subject":"Food","subject_confidence":0.40819552540779114},"children":[]}]}