{"analysis":{"attitude":"Neutral","attitude_confidence":0.7455764412879944,"subject":"Other","subject_confidence":0.7538244277238846},"children":[{"analysis":{"attitude":"Mocking","attitude_confidence":0.3068753778934479,"subject":"Joke","subject_confidence":0.8909167051315308},"children":[{"analysis":{"attitude":"Neutral","attitude_confidence":0.8021065592765808,"subject":"Other","subject_confidence":0.7018994987010956},"children":[]},{"analysis":{"attitude":"Mocking","attitude_confidence":0.37468650937080383,"subject":"Joke","subject_confidence":0.6933073997497559},"children":[]}]},{"analysis":{"attitude":"Inquisitive","attitude_confidence":0.4101187288761139,"subject":"Other","subject_confidence":0.7105026841163635},"children":[]},{"analysis":{"attitude":"Neutral","attitude_confidence":0.7963773161172867,"subject":"Other","subject_confidence":0.7936554253101349},"children":[]},{"analysis":{"attitude":"Neutral","attitude_confidence":0.7023707330226898,"subject":"Other","subject_confidence":0.7217754423618317},"children":[{"analysis":{"attitude":"Inquisitive","attitude_confidence":0.370968222618103,"subject":"Other","subject_confidence":0.79158915579319},"children":[]}]},{"analysis":{"attitude":"Disagreement","attitude_confidence":0.31749284267425537,"subject":"Joke","subject_confidence":0.6276770830154419},"children":[]},{"analysis":{"attitude":"Neutral","attitude_confidence":0.8282816559076309,"subject":"Other","subject_confidence":0.8543262928724289},"children":[]},{"analysis":{"attitude":"Neutral","attitude_confidence":0.7869661599397659,"subject":"Other","subject_confidence":0.7934383898973465},"children":[]}]}