{"analysis":{"attitude":"Neutral","attitude_confidence":0.7487447559833527,"subject":"Discussion","subject_confidence":0.3570442199707031},"children":[{"analysis":{"attitude":"Agreement","attitude_confidence":0.31972527503967285,"subject":"Discussion","subject_confidence":0.41559723019599915},"children":[]},{"analysis":{"attitude":"Condemnation","attitude_confidence":0.4448556900024414,"subject":"Other","subject_confidence":0.7804515510797501},"children":[]},{"analysis":{"attitude":"Condemnation","attitude_confidence":0.41747453808784485,"subject":"Other","subject_confidence":0.7370080053806305},"children":[{"analysis":{"attitude":"Inquisitive","attitude_confidence":0.6559740304946899,"subject":"Joke","subject_confidence":0.35964342951774597},"children":[{"analysis":{"attitude":"Inquisitive","attitude_confidence":0.6367127895355225,"subject":"Discussion","subject_confidence":0.3019865155220032},"children":[]},{"analysis":{"attitude":"Neutral","attitude_confidence":0.7649417817592621,"subject":"Other","subject_confidence":0.7022161781787872},"children":[]}]}]}]}