{"analysis":{"attitude":"Inquisitive","attitude_confidence":0.4024279713630676,"subject":"Other","subject_confidence":0.7809847295284271},"children":[{"analysis":{"attitude":"Neutral","attitude_confidence":0.8310338854789734,"subject":"Other","subject_confidence":0.7431536316871643},"children":[]},{"analysis":{"attitude":"Neutral","attitude_confidence":0.7650901824235916,"subject":"Other","subject_confidence":0.8469029664993286},"children":[]},{"analysis":{"attitude":"Mocking","attitude_confidence":0.45433342456817627,"subject":"Joke","subject_confidence":0.4099794328212738},"children":[]},{"analysis":{"attitude":"Neutral","attitude_confidence":0.8404339700937271,"subject":"Other","subject_confidence":0.7953435331583023},"children":[]}]}