{"analysis":{"attitude":"Neutral","attitude_confidence":0.7576226890087128,"subject":"Other","subject_confidence":0.716825544834137},"children":[{"analysis":{"attitude":"Neutral","attitude_confidence":0.7230826020240784,"subject":"Other","subject_confidence":0.7769066691398621},"children":[]},{"analysis":{"attitude":"Neutral","attitude_confidence":0.7198533415794373,"subject":"Technology","subject_confidence":0.30421140789985657},"children":[{"analysis":{"attitude":"Praise","attitude_confidence":0.5367709994316101,"subject":"Other","subject_confidence":0.8200380802154541},"children":[]}]},{"analysis":{"attitude":"Neutral","attitude_confidence":0.7646468132734299,"subject":"Other","subject_confidence":0.7967830896377563},"children":[{"analysis":{"attitude":"Agreement","attitude_confidence":0.49411970376968384,"subject":"Other","subject_confidence":0.7054233253002167},"children":[]}]},{"analysis":{"attitude":"Neutral","attitude_confidence":0.7055680453777313,"subject":"Other","subject_confidence":0.8164088129997253},"children":[{"analysis":{"attitude":"Disagreement","attitude_confidence":0.330426961183548,"subject":"Other","subject_confidence":0.8032815903425217},"children":[]}]},{"analysis":{"attitude":"Neutral","attitude_confidence":0.7672573924064636,"subject":"Other","subject_confidence":0.8162575513124466},"children":[{"analysis":{"attitude":"Annoyed","attitude_confidence":0.3061492443084717,"subject":"Other","subject_confidence":0.7638204842805862},"children":[]}]}]}