{"analysis":{"attitude":"Neutral","attitude_confidence":0.0,"subject":"Other","subject_confidence":0.0},"children":[{"analysis":{"attitude":"Neutral","attitude_confidence":0.8042869120836258,"subject":"Other","subject_confidence":0.8242532908916473},"children":[]},{"analysis":{"attitude":"Praise","attitude_confidence":0.8572726249694824,"subject":"Other","subject_confidence":0.7746337950229645},"children":[]},{"analysis":{"attitude":"Praise","attitude_confidence":0.6657614707946777,"subject":"Other","subject_confidence":0.7559920102357864},"children":[]}]}