{"analysis":{"attitude":"Neutral","attitude_confidence":0.0,"subject":"Other","subject_confidence":0.0},"children":[{"analysis":{"attitude":"Neutral","attitude_confidence":0.7637806385755539,"subject":"Joke","subject_confidence":0.3202703297138214},"children":[{"analysis":{"attitude":"Neutral","attitude_confidence":0.7065261900424957,"subject":"Animals","subject_confidence":0.36907416582107544},"children":[]}]},{"analysis":{"attitude":"Neutral","attitude_confidence":0.729890376329422,"subject":"Food","subject_confidence":0.5513696074485779},"children":[{"analysis":{"attitude":"Inquisitive","attitude_confidence":0.30284416675567627,"subject":"Joke","subject_confidence":0.32869842648506165},"children":[]},{"analysis":{"attitude":"Neutral","attitude_confidence":0.7609217017889023,"subject":"Personal","subject_confidence":0.49038660526275635},"children":[]}]},{"analysis":{"attitude":"Neutral","attitude_confidence":0.7483473122119904,"subject":"Animals","subject_confidence":0.44929441809654236},"children":[{"analysis":{"attitude":"Neutral","attitude_confidence":0.745276004076004,"subject":"Other","subject_confidence":0.703223317861557},"children":[]}]},{"analysis":{"attitude":"Neutral","attitude_confidence":0.725851833820343,"subject":"Other","subject_confidence":0.7068881690502167},"children":[]},{"analysis":{"attitude":"Praise","attitude_confidence":0.7140459418296814,"subject":"Other","subject_confidence":0.7604212909936905},"children":[]},{"analysis":{"attitude":"Neutral","attitude_confidence":0.7037726640701294,"subject":"Other","subject_confidence":0.7351141571998596},"children":[]}]}