{"analysis":{"attitude":"Neutral","attitude_confidence":0.0,"subject":"Other","subject_confidence":0.0},"children":[{"analysis":{"attitude":"Neutral","attitude_confidence":0.7996819913387299,"subject":"Joke","subject_confidence":0.596928060054779},"children":[{"analysis":{"attitude":"Neutral","attitude_confidence":0.8197331130504608,"subject":"Other","subject_confidence":0.8439085334539413},"children":[{"analysis":{"attitude":"Praise","attitude_confidence":0.3080720901489258,"subject":"Other","subject_confidence":0.7582815438508987},"children":[]}]}]},{"analysis":{"attitude":"Neutral","attitude_confidence":0.7375079989433289,"subject":"Personal","subject_confidence":0.6204325556755066},"children":[{"analysis":{"attitude":"Neutral","attitude_confidence":0.714282363653183,"subject":"Joke","subject_confidence":0.40162116289138794},"children":[]}]},{"analysis":{"attitude":"Agreement","attitude_confidence":0.45720174908638,"subject":"Other","subject_confidence":0.7433950304985046},"children":[]},{"analysis":{"attitude":"Neutral","attitude_confidence":0.7771136164665222,"subject":"Other","subject_confidence":0.7157841920852661},"children":[]},{"analysis":{"attitude":"Neutral","attitude_confidence":0.7753450721502304,"subject":"Other","subject_confidence":0.7988068759441376},"children":[{"analysis":{"attitude":"Neutral","attitude_confidence":0.8118465393781662,"subject":"Joke","subject_confidence":0.48237332701683044},"children":[{"analysis":{"attitude":"Inquisitive","attitude_confidence":0.3044375777244568,"subject":"Other","subject_confidence":0.709358274936676},"children":[]}]}]}]}