{"analysis":{"attitude":"Neutral","attitude_confidence":0.0,"subject":"Other","subject_confidence":0.0},"children":[{"analysis":{"attitude":"Inquisitive","attitude_confidence":0.4949229955673218,"subject":"Discussion","subject_confidence":0.3619815409183502},"children":[]},{"analysis":{"attitude":"Praise","attitude_confidence":0.3353385627269745,"subject":"Other","subject_confidence":0.7751145511865616},"children":[]},{"analysis":{"attitude":"Neutral","attitude_confidence":0.8048907369375229,"subject":"Discussion","subject_confidence":0.46626120805740356},"children":[]},{"analysis":{"attitude":"Agreement","attitude_confidence":0.37872186303138733,"subject":"Other","subject_confidence":0.7184345722198486},"children":[]},{"analysis":{"attitude":"Inquisitive","attitude_confidence":0.3571062386035919,"subject":"Other","subject_confidence":0.7119454741477966},"children":[]}]}