{"analysis":{"attitude":"Annoyed","attitude_confidence":0.36405789852142334,"subject":"Joke","subject_confidence":0.42234811186790466},"children":[{"analysis":{"attitude":"Disagreement","attitude_confidence":0.3312007486820221,"subject":"Other","subject_confidence":0.7630697339773178},"children":[]},{"analysis":{"attitude":"Neutral","attitude_confidence":0.7401711940765381,"subject":"Other","subject_confidence":0.7199032306671143},"children":[]},{"analysis":{"attitude":"Annoyed","attitude_confidence":0.397574245929718,"subject":"Other","subject_confidence":0.7190399765968323},"children":[]}]}