{"analysis":{"attitude":"Neutral","attitude_confidence":0.0,"subject":"Other","subject_confidence":0.0},"children":[{"analysis":{"attitude":"Neutral","attitude_confidence":0.8101683855056763,"subject":"Other","subject_confidence":0.7324919998645782},"children":[]},{"analysis":{"attitude":"Inquisitive","attitude_confidence":0.39862966537475586,"subject":"Discussion","subject_confidence":0.36326995491981506},"children":[{"analysis":{"attitude":"Inquisitive","attitude_confidence":0.46881935000419617,"subject":"Discussion","subject_confidence":0.3139597177505493},"children":[]}]},{"analysis":{"attitude":"Neutral","attitude_confidence":0.7005423307418823,"subject":"Other","subject_confidence":0.8257717788219452},"children":[]},{"analysis":{"attitude":"Annoyed","attitude_confidence":0.3063208758831024,"subject":"Other","subject_confidence":0.8028800189495087},"children":[]},{"analysis":{"attitude":"Neutral","attitude_confidence":0.7616932094097137,"subject":"Other","subject_confidence":0.7367978096008301},"children":[{"analysis":{"attitude":"Neutral","attitude_confidence":0.8093021661043167,"subject":"Joke","subject_confidence":0.505220890045166},"children":[]}]},{"analysis":{"attitude":"Neutral","attitude_confidence":0.7151168882846832,"subject":"Other","subject_confidence":0.7879566252231598},"children":[{"analysis":{"attitude":"Neutral","attitude_confidence":0.7679223865270615,"subject":"Politics","subject_confidence":0.4318046271800995},"children":[]},{"analysis":{"attitude":"Neutral","attitude_confidence":0.8051921278238297,"subject":"Other","subject_confidence":0.7249302268028259},"children":[]}]}]}