{"analysis":{"attitude":"Neutral","attitude_confidence":0.7094391584396362,"subject":"Personal","subject_confidence":0.31935468316078186},"children":[{"analysis":{"attitude":"Praise","attitude_confidence":0.5057749152183533,"subject":"Other","subject_confidence":0.8265270590782166},"children":[]},{"analysis":{"attitude":"Inquisitive","attitude_confidence":0.33834484219551086,"subject":"Discussion","subject_confidence":0.4379662573337555},"children":[{"analysis":{"attitude":"Inquisitive","attitude_confidence":0.4821055829524994,"subject":"Discussion","subject_confidence":0.4133288264274597},"children":[]}]},{"analysis":{"attitude":"Neutral","attitude_confidence":0.7909076660871506,"subject":"Other","subject_confidence":0.8202382475137711},"children":[]},{"analysis":{"attitude":"Inquisitive","attitude_confidence":0.4016331136226654,"subject":"Other","subject_confidence":0.7985701560974121},"children":[{"analysis":{"attitude":"Inquisitive","attitude_confidence":0.47904184460639954,"subject":"Other","subject_confidence":0.7436680793762207},"children":[{"analysis":{"attitude":"Neutral","attitude_confidence":0.733519434928894,"subject":"Other","subject_confidence":0.8326709270477295},"children":[]},{"analysis":{"attitude":"Neutral","attitude_confidence":0.7313492298126221,"subject":"Other","subject_confidence":0.8110138177871704},"children":[]}]}]}]}