{"analysis":{"attitude":"Neutral","attitude_confidence":0.0,"subject":"Other","subject_confidence":0.0},"children":[{"analysis":{"attitude":"Inquisitive","attitude_confidence":0.4879620373249054,"subject":"Discussion","subject_confidence":0.3591686487197876},"children":[]},{"analysis":{"attitude":"Inquisitive","attitude_confidence":0.5115198493003845,"subject":"Discussion","subject_confidence":0.39155545830726624},"children":[]},{"analysis":{"attitude":"Neutral","attitude_confidence":0.8410904109477997,"subject":"Other","subject_confidence":0.8382617682218552},"children":[]},{"analysis":{"attitude":"Praise","attitude_confidence":0.6972723603248596,"subject":"Other","subject_confidence":0.7681702077388763},"children":[]},{"analysis":{"attitude":"Neutral","attitude_confidence":0.7134425342082977,"subject":"Other","subject_confidence":0.7092551589012146},"children":[]},{"analysis":{"attitude":"Praise","attitude_confidence":0.6733474135398865,"subject":"Other","subject_confidence":0.7506693750619888},"children":[]}]}