{"analysis":{"attitude":"Neutral","attitude_confidence":0.7052049040794373,"subject":"Other","subject_confidence":0.8308604806661606},"children":[{"analysis":{"attitude":"Neutral","attitude_confidence":0.7605171799659729,"subject":"Discussion","subject_confidence":0.3423241376876831},"children":[]},{"analysis":{"attitude":"Inquisitive","attitude_confidence":0.3282318115234375,"subject":"Other","subject_confidence":0.7790471315383911},"children":[{"analysis":{"attitude":"Disagreement","attitude_confidence":0.30071383714675903,"subject":"Other","subject_confidence":0.8111162632703781},"children":[{"analysis":{"attitude":"Neutral","attitude_confidence":0.7608250230550766,"subject":"Other","subject_confidence":0.8096372783184052},"children":[]}]},{"analysis":{"attitude":"Praise","attitude_confidence":0.8138564229011536,"subject":"Other","subject_confidence":0.7367493808269501},"children":[]},{"analysis":{"attitude":"Neutral","attitude_confidence":0.8081220388412476,"subject":"Joke","subject_confidence":0.562623143196106},"children":[{"analysis":{"attitude":"Neutral","attitude_confidence":0.7669884413480759,"subject":"Other","subject_confidence":0.781789243221283},"children":[{"analysis":{"attitude":"Neutral","attitude_confidence":0.7968135625123978,"subject":"Other","subject_confidence":0.7319858074188232},"children":[{"analysis":{"attitude":"Neutral","attitude_confidence":0.7021654546260834,"subject":"Discussion","subject_confidence":0.34711238741874695},"children":[]}]}]},{"analysis":{"attitude":"Neutral","attitude_confidence":0.7932987958192825,"subject":"Other","subject_confidence":0.7630860656499863},"children":[]}]}]}]}