{"analysis":{"attitude":"Disagreement","attitude_confidence":0.48386460542678833,"subject":"Other","subject_confidence":0.728035569190979},"children":[{"analysis":{"attitude":"Neutral","attitude_confidence":0.7868781387805939,"subject":"Sports","subject_confidence":0.3236371874809265},"children":[]},{"analysis":{"attitude":"Neutral","attitude_confidence":0.7512694150209427,"subject":"Other","subject_confidence":0.7515112310647964},"children":[]},{"analysis":{"attitude":"Praise","attitude_confidence":0.35422563552856445,"subject":"Other","subject_confidence":0.8083714991807938},"children":[]},{"analysis":{"attitude":"Disagreement","attitude_confidence":0.46257534623146057,"subject":"Other","subject_confidence":0.825279176235199},"children":[]},{"analysis":{"attitude":"Neutral","attitude_confidence":0.7793633788824081,"subject":"Other","subject_confidence":0.7500472217798233},"children":[]},{"analysis":{"attitude":"Neutral","attitude_confidence":0.7781887948513031,"subject":"Other","subject_confidence":0.7679889500141144},"children":[]},{"analysis":{"attitude":"Neutral","attitude_confidence":0.7361871302127838,"subject":"Other","subject_confidence":0.7414968907833099},"children":[]},{"analysis":{"attitude":"Neutral","attitude_confidence":0.7193948924541473,"subject":"Other","subject_confidence":0.8255545496940613},"children":[]},{"analysis":{"attitude":"Neutral","attitude_confidence":0.7888061851263046,"subject":"Other","subject_confidence":0.8122970759868622},"children":[]},{"analysis":{"attitude":"Neutral","attitude_confidence":0.784549281001091,"subject":"Other","subject_confidence":0.7910958230495453},"children":[]}]}