{"analysis":{"attitude":"Neutral","attitude_confidence":0.0,"subject":"Other","subject_confidence":0.0},"children":[{"analysis":{"attitude":"Neutral","attitude_confidence":0.8138532340526581,"subject":"Other","subject_confidence":0.8186043798923492},"children":[]},{"analysis":{"attitude":"Neutral","attitude_confidence":0.7979830801486969,"subject":"Other","subject_confidence":0.7900398224592209},"children":[]},{"analysis":{"attitude":"Neutral","attitude_confidence":0.8153500854969025,"subject":"Joke","subject_confidence":0.5722540616989136},"children":[]},{"analysis":{"attitude":"Neutral","attitude_confidence":0.7776605486869812,"subject":"Other","subject_confidence":0.737510621547699},"children":[]},{"analysis":{"attitude":"Neutral","attitude_confidence":0.7399146854877472,"subject":"Other","subject_confidence":0.8083070367574692},"children":[{"analysis":{"attitude":"Neutral","attitude_confidence":0.7210955619812012,"subject":"Other","subject_confidence":0.8051368892192841},"children":[]}]},{"analysis":{"attitude":"Agreement","attitude_confidence":0.5668535828590393,"subject":"Other","subject_confidence":0.8424334526062012},"children":[]},{"analysis":{"attitude":"Inquisitive","attitude_confidence":0.6089726686477661,"subject":"Other","subject_confidence":0.7029307186603546},"children":[]},{"analysis":{"attitude":"Neutral","attitude_confidence":0.7784697711467743,"subject":"Other","subject_confidence":0.7313008904457092},"children":[]},{"analysis":{"attitude":"Neutral","attitude_confidence":0.7585496008396149,"subject":"Other","subject_confidence":0.7009060382843018},"children":[]}]}