{"analysis":{"attitude":"Neutral","attitude_confidence":0.0,"subject":"Other","subject_confidence":0.0},"children":[{"analysis":{"attitude":"Neutral","attitude_confidence":0.7948583662509918,"subject":"Politics","subject_confidence":0.32903167605400085},"children":[]},{"analysis":{"attitude":"Annoyed","attitude_confidence":0.4741215407848358,"subject":"Other","subject_confidence":0.7679980993270874},"children":[{"analysis":{"attitude":"Disagreement","attitude_confidence":0.31052398681640625,"subject":"Other","subject_confidence":0.7879515886306763},"children":[]}]},{"analysis":{"attitude":"Inquisitive","attitude_confidence":0.35199207067489624,"subject":"Other","subject_confidence":0.8253414779901505},"children":[{"analysis":{"attitude":"Agreement","attitude_confidence":0.4274362027645111,"subject":"Other","subject_confidence":0.7908952981233597},"children":[]}]},{"analysis":{"attitude":"Praise","attitude_confidence":0.5358584523200989,"subject":"Other","subject_confidence":0.794819712638855},"children":[]},{"analysis":{"attitude":"Neutral","attitude_confidence":0.7116283178329468,"subject":"Joke","subject_confidence":0.38639235496520996},"children":[]},{"analysis":{"attitude":"Neutral","attitude_confidence":0.7569173872470856,"subject":"Food","subject_confidence":0.41615307331085205},"children":[]},{"analysis":{"attitude":"Neutral","attitude_confidence":0.7654736489057541,"subject":"Other","subject_confidence":0.7594525068998337},"children":[]},{"analysis":{"attitude":"Neutral","attitude_confidence":0.7823485732078552,"subject":"Technology","subject_confidence":0.4078088700771332},"children":[]}]}