{"analysis":{"attitude":"Neutral","attitude_confidence":0.0,"subject":"Other","subject_confidence":0.0},"children":[{"analysis":{"attitude":"Neutral","attitude_confidence":0.7184644341468811,"subject":"Other","subject_confidence":0.7599321901798248},"children":[]},{"analysis":{"attitude":"Neutral","attitude_confidence":0.7717884033918381,"subject":"Other","subject_confidence":0.7705948650836945},"children":[{"analysis":{"attitude":"Inquisitive","attitude_confidence":0.33299845457077026,"subject":"Other","subject_confidence":0.7725767344236374},"children":[]}]}]}