{"analysis":{"attitude":"Neutral","attitude_confidence":0.0,"subject":"Other","subject_confidence":0.0},"children":[{"analysis":{"attitude":"Disagreement","attitude_confidence":0.3279252350330353,"subject":"Other","subject_confidence":0.8411345481872559},"children":[]},{"analysis":{"attitude":"Inquisitive","attitude_confidence":0.3253144323825836,"subject":"Other","subject_confidence":0.7853171974420547},"children":[]},{"analysis":{"attitude":"Neutral","attitude_confidence":0.7735954374074936,"subject":"Other","subject_confidence":0.8219244033098221},"children":[]}]}