{"analysis":{"attitude":"Neutral","attitude_confidence":0.0,"subject":"Other","subject_confidence":0.0},"children":[{"analysis":{"attitude":"Inquisitive","attitude_confidence":0.5078904032707214,"subject":"Other","subject_confidence":0.7860317975282669},"children":[]},{"analysis":{"attitude":"Neutral","attitude_confidence":0.7301320433616638,"subject":"Discussion","subject_confidence":0.3457143306732178},"children":[{"analysis":{"attitude":"Inquisitive","attitude_confidence":0.42213931679725647,"subject":"Other","subject_confidence":0.7833200991153717},"children":[{"analysis":{"attitude":"Neutral","attitude_confidence":0.7542935162782669,"subject":"Discussion","subject_confidence":0.3228342831134796},"children":[{"analysis":{"attitude":"Inquisitive","attitude_confidence":0.36265867948532104,"subject":"Other","subject_confidence":0.772828683257103},"children":[]}]}]}]},{"analysis":{"attitude":"Mocking","attitude_confidence":0.49438413977622986,"subject":"Joke","subject_confidence":0.6004186272621155},"children":[{"analysis":{"attitude":"Neutral","attitude_confidence":0.7433577477931976,"subject":"Other","subject_confidence":0.793309286236763},"children":[]}]},{"analysis":{"attitude":"Neutral","attitude_confidence":0.7461215257644653,"subject":"Other","subject_confidence":0.7991566210985184},"children":[{"analysis":{"attitude":"Disagreement","attitude_confidence":0.30757609009742737,"subject":"Discussion","subject_confidence":0.447449266910553},"children":[]}]},{"analysis":{"attitude":"Neutral","attitude_confidence":0.7185132205486298,"subject":"Other","subject_confidence":0.8062922954559326},"children":[]}]}