{"analysis":{"attitude":"Neutral","attitude_confidence":0.0,"subject":"Other","subject_confidence":0.0},"children":[{"analysis":{"attitude":"Neutral","attitude_confidence":0.7974631935358047,"subject":"Other","subject_confidence":0.8590322434902191},"children":[{"analysis":{"attitude":"Neutral","attitude_confidence":0.7640823721885681,"subject":"Other","subject_confidence":0.7564069479703903},"children":[{"analysis":{"attitude":"Neutral","attitude_confidence":0.7895884811878204,"subject":"Animals","subject_confidence":0.3506351113319397},"children":[]}]}]},{"analysis":{"attitude":"Disagreement","attitude_confidence":0.3029259443283081,"subject":"Personal","subject_confidence":0.38819563388824463},"children":[{"analysis":{"attitude":"Neutral","attitude_confidence":0.7370848059654236,"subject":"Other","subject_confidence":0.8376507759094238},"children":[]}]},{"analysis":{"attitude":"Inquisitive","attitude_confidence":0.554916262626648,"subject":"Movies","subject_confidence":0.3152211308479309},"children":[{"analysis":{"attitude":"Praise","attitude_confidence":0.31378528475761414,"subject":"Other","subject_confidence":0.7157294750213623},"children":[]}]},{"analysis":{"attitude":"Inquisitive","attitude_confidence":0.5589383840560913,"subject":"Other","subject_confidence":0.7319804430007935},"children":[{"analysis":{"attitude":"Agreement","attitude_confidence":0.4986873269081116,"subject":"Other","subject_confidence":0.7860517054796219},"children":[]}]},{"analysis":{"attitude":"Neutral","attitude_confidence":0.7796801179647446,"subject":"Other","subject_confidence":0.8065840750932693},"children":[]}]}